reader/__init__.py
reader/__main__.py
reader/articles.xml
reader/config.cfg
reader/feed.py
reader/main.py
reader/viewer.py
mauroquinteroos_reader-1.2.0.dist-info/LICENSE.txt
mauroquinteroos_reader-1.2.0.dist-info/METADATA
mauroquinteroos_reader-1.2.0.dist-info/WHEEL
mauroquinteroos_reader-1.2.0.dist-info/entry_points.txt
mauroquinteroos_reader-1.2.0.dist-info/top_level.txt
mauroquinteroos_reader-1.2.0.dist-info/RECORD
