Metadata-Version: 2.1
Name: mauroquinteroos-reader
Version: 1.2.0
Summary: Paquete de prueba de Mauro Quinteros
Home-page: https://github.com/mauroquinteroos/mauroquinteroos-reader
Author: Mauro Quinteros
Author-email: quinterosmauro0599@gmail.com
License: MIT
Project-URL: Docs, https://mauroquinteroos.github.io/mauroquinteroos-reader/
Project-URL: Issues, https://github.com/mauroquinteroos/mauroquinteroos-reader/issues
Platform: UNKNOWN
Classifier: License :: OSI Approved :: MIT License
Classifier: Programming Language :: Python :: 3.6
Requires-Python: >=3.6
License-File: LICENSE.txt
Requires-Dist: feedparser
Requires-Dist: html2text
